pypairix.cpython-38-darwin.so
pypairix-0.3.9.dist-info/LICENSE.txt
pypairix-0.3.9.dist-info/METADATA
pypairix-0.3.9.dist-info/WHEEL
pypairix-0.3.9.dist-info/top_level.txt
pypairix-0.3.9.dist-info/RECORD
