Metadata-Version: 2.1
Name: pypairix
Version: 0.3.9
Summary: Pypairix is a Python module for fast querying on a pairix-indexed bgzipped text file that contains a pair of genomic coordinates per line. For more information, see: https://github.com/4dn-dcic/pairix/blob/master/README.md.
Home-page: https://github.com/4dn-dcic/pairix
Download-URL: https://github.com/4dn-dcic/pairix/tarball/0.3.9
Author: Soo Lee, Carl Vitzthum
Author-email: duplexa@gmail.com
License: MIT
Keywords: pairix,tabix,bgzip,bioinformatics,genomics,hi-c
Classifier: Programming Language :: Python :: 2.7
Classifier: Programming Language :: Python :: 3
Classifier: Development Status :: 4 - Beta
Classifier: Intended Audience :: Developers
Classifier: Intended Audience :: Science/Research
Classifier: License :: OSI Approved :: MIT License
Classifier: Operating System :: OS Independent
Classifier: Programming Language :: C
Classifier: Topic :: Software Development :: Libraries :: Python Modules
Classifier: Topic :: Scientific/Engineering :: Bio-Informatics
License-File: LICENSE.txt
